enochecker_test/__init__.py
enochecker_test/__main__.py
enochecker_test/conftest.py
enochecker_test/main.py
enochecker_test/tests.py
enochecker_test-0.10.1.dist-info/LICENSE
enochecker_test-0.10.1.dist-info/METADATA
enochecker_test-0.10.1.dist-info/WHEEL
enochecker_test-0.10.1.dist-info/entry_points.txt
enochecker_test-0.10.1.dist-info/RECORD
