Metadata-Version: 2.3
Name: enochecker_test
Version: 0.10.1
Summary: Library to help testing checker scripts based on enochecker
License: MIT
Author: ldruschk
Author-email: ldrushk@posteo.de
Requires-Python: >=3.8.1,<=4.0
Classifier: Development Status :: 3 - Alpha
Classifier: License :: OSI Approved :: MIT License
Classifier: Programming Language :: Python :: 3
Classifier: Programming Language :: Python :: 3.9
Classifier: Programming Language :: Python :: 3.10
Classifier: Programming Language :: Python :: 3.11
Classifier: Programming Language :: Python :: 3.12
Classifier: Programming Language :: Python :: 3.13
Requires-Dist: enochecker-core (>=0.10.0,<0.11.0)
Requires-Dist: jsons (>=1.6.3,<2.0.0)
Requires-Dist: pytest (>=8.2.1,<9.0.0)
Requires-Dist: requests (>=2.32.3,<3.0.0)
Project-URL: Homepage, https://github.com/enowars/enochecker_test
Project-URL: Repository, https://github.com/enowars/enochecker_test
